czech_sort/__init__.py
czech_sort/__main__.py
czech_sort/impl.py
czech_sort-1.1.0.dist-info/LICENSE
czech_sort-1.1.0.dist-info/METADATA
czech_sort-1.1.0.dist-info/WHEEL
czech_sort-1.1.0.dist-info/top_level.txt
czech_sort-1.1.0.dist-info/zip-safe
czech_sort-1.1.0.dist-info/RECORD
