Metadata-Version: 2.1
Name: czech-sort
Version: 1.1.0
Summary: Text sorting function for the Czech language
Home-page: https://github.com/encukou/czech-sort
Author: Petr Viktorin
Author-email: encukou@gmail.com
Classifier: Intended Audience :: Developers
Classifier: License :: OSI Approved :: MIT License
Classifier: Operating System :: OS Independent
Classifier: Programming Language :: Python
Classifier: Programming Language :: Python :: 3
Requires-Python: >=3.5
License-File: LICENSE
Provides-Extra: test
Requires-Dist: pytest ; extra == 'test'
Requires-Dist: hypothesis ; extra == 'test'
